[
	{
		"name": "Saber I",
		"unitType": "Sword",
		"uniqueTo": "Chaldea",
		"movement": 3,
		"strength": 40,
		"cost": 990,
		"uniques": ["Unbuildable"],
	},
	{
		"name": "Archer I",
		"unitType": "Archery",
		"uniqueTo": "Chaldea",
		"movement": 2,
		"strength": 30,
		"rangedStrength": 15,
		"cost": 990,
		"uniques": ["Unbuildable"],
	},
	{
		"name": "Lancer I",
		"unitType": "Sword",
		"uniqueTo": "Chaldea",
		"movement": 4,
		"strength": 36,
		"cost": 990,
		"uniques": ["[+50]% Strength <vs [Mounted] units>", "Unbuildable"],
	},
]
